{
	"$schema": "http://schema.management.azure.com/schemas/2015-01-01/deploymentTemplate.json#",
	"contentVersion": "1.0.0.0",
	"parameters": {
		"factoryName": {
			"type": "string",
			"metadata": "Data Factory name",
			"defaultValue": "KUSONG-PROD-IR"
		},
		"LinkedService3785_connectionString": {
			"type": "secureString",
			"metadata": "Secure string for 'connectionString' of 'LinkedService3785'"
		},
		"LinkedService3786_connectionString": {
			"type": "secureString",
			"metadata": "Secure string for 'connectionString' of 'LinkedService3786'"
		},
		"LinkedService3787_connectionString": {
			"type": "secureString",
			"metadata": "Secure string for 'connectionString' of 'LinkedService3787'"
		},
		"LinkedService3788_connectionString": {
			"type": "secureString",
			"metadata": "Secure string for 'connectionString' of 'LinkedService3788'"
		},
		"LinkedService3789_connectionString": {
			"type": "secureString",
			"metadata": "Secure string for 'connectionString' of 'LinkedService3789'"
		},
		"LinkedService379_connectionString": {
			"type": "secureString",
			"metadata": "Secure string for 'connectionString' of 'LinkedService379'"
		},
		"LinkedService3790_connectionString": {
			"type": "secureString",
			"metadata": "Secure string for 'connectionString' of 'LinkedService3790'"
		},
		"LinkedService3791_connectionString": {
			"type": "secureString",
			"metadata": "Secure string for 'connectionString' of 'LinkedService3791'"
		},
		"LinkedService3792_connectionString": {
			"type": "secureString",
			"metadata": "Secure string for 'connectionString' of 'LinkedService3792'"
		},
		"LinkedService3793_connectionString": {
			"type": "secureString",
			"metadata": "Secure string for 'connectionString' of 'LinkedService3793'"
		},
		"LinkedService3794_connectionString": {
			"type": "secureString",
			"metadata": "Secure string for 'connectionString' of 'LinkedService3794'"
		},
		"LinkedService3795_connectionString": {
			"type": "secureString",
			"metadata": "Secure string for 'connectionString' of 'LinkedService3795'"
		},
		"LinkedService3796_connectionString": {
			"type": "secureString",
			"metadata": "Secure string for 'connectionString' of 'LinkedService3796'"
		},
		"LinkedService3797_connectionString": {
			"type": "secureString",
			"metadata": "Secure string for 'connectionString' of 'LinkedService3797'"
		},
		"LinkedService3798_connectionString": {
			"type": "secureString",
			"metadata": "Secure string for 'connectionString' of 'LinkedService3798'"
		},
		"LinkedService3799_connectionString": {
			"type": "secureString",
			"metadata": "Secure string for 'connectionString' of 'LinkedService3799'"
		},
		"LinkedService38_connectionString": {
			"type": "secureString",
			"metadata": "Secure string for 'connectionString' of 'LinkedService38'"
		},
		"LinkedService380_connectionString": {
			"type": "secureString",
			"metadata": "Secure string for 'connectionString' of 'LinkedService380'"
		},
		"LinkedService3800_connectionString": {
			"type": "secureString",
			"metadata": "Secure string for 'connectionString' of 'LinkedService3800'"
		},
		"LinkedService3801_connectionString": {
			"type": "secureString",
			"metadata": "Secure string for 'connectionString' of 'LinkedService3801'"
		}
	},
	"variables": {
		"factoryId": "[concat('Microsoft.DataFactory/factories/', parameters('factoryName'))]"
	},
	"resources": [
		{
			"name": "[concat(parameters('factoryName'), '/LinkedService3785')]",
			"type": "Microsoft.DataFactory/factories/linkedServices",
			"apiVersion": "2018-06-01",
			"properties": {
				"annotations": [],
				"type": "AzureBlobStorage",
				"typeProperties": {
					"connectionString": "[parameters('LinkedService3785_connectionString')]"
				},
				"connectVia": {
					"referenceName": "TestManyLS",
					"type": "IntegrationRuntimeReference"
				}
			},
			"dependsOn": []
		},
		{
			"name": "[concat(parameters('factoryName'), '/LinkedService3786')]",
			"type": "Microsoft.DataFactory/factories/linkedServices",
			"apiVersion": "2018-06-01",
			"properties": {
				"annotations": [],
				"type": "AzureBlobStorage",
				"typeProperties": {
					"connectionString": "[parameters('LinkedService3786_connectionString')]"
				},
				"connectVia": {
					"referenceName": "TestManyLS",
					"type": "IntegrationRuntimeReference"
				}
			},
			"dependsOn": []
		},
		{
			"name": "[concat(parameters('factoryName'), '/LinkedService3787')]",
			"type": "Microsoft.DataFactory/factories/linkedServices",
			"apiVersion": "2018-06-01",
			"properties": {
				"annotations": [],
				"type": "AzureBlobStorage",
				"typeProperties": {
					"connectionString": "[parameters('LinkedService3787_connectionString')]"
				},
				"connectVia": {
					"referenceName": "TestManyLS",
					"type": "IntegrationRuntimeReference"
				}
			},
			"dependsOn": []
		},
		{
			"name": "[concat(parameters('factoryName'), '/LinkedService3788')]",
			"type": "Microsoft.DataFactory/factories/linkedServices",
			"apiVersion": "2018-06-01",
			"properties": {
				"annotations": [],
				"type": "AzureBlobStorage",
				"typeProperties": {
					"connectionString": "[parameters('LinkedService3788_connectionString')]"
				},
				"connectVia": {
					"referenceName": "TestManyLS",
					"type": "IntegrationRuntimeReference"
				}
			},
			"dependsOn": []
		},
		{
			"name": "[concat(parameters('factoryName'), '/LinkedService3789')]",
			"type": "Microsoft.DataFactory/factories/linkedServices",
			"apiVersion": "2018-06-01",
			"properties": {
				"annotations": [],
				"type": "AzureBlobStorage",
				"typeProperties": {
					"connectionString": "[parameters('LinkedService3789_connectionString')]"
				},
				"connectVia": {
					"referenceName": "TestManyLS",
					"type": "IntegrationRuntimeReference"
				}
			},
			"dependsOn": []
		},
		{
			"name": "[concat(parameters('factoryName'), '/LinkedService379')]",
			"type": "Microsoft.DataFactory/factories/linkedServices",
			"apiVersion": "2018-06-01",
			"properties": {
				"annotations": [],
				"type": "AzureBlobStorage",
				"typeProperties": {
					"connectionString": "[parameters('LinkedService379_connectionString')]"
				},
				"connectVia": {
					"referenceName": "TestManyLS",
					"type": "IntegrationRuntimeReference"
				}
			},
			"dependsOn": []
		},
		{
			"name": "[concat(parameters('factoryName'), '/LinkedService3790')]",
			"type": "Microsoft.DataFactory/factories/linkedServices",
			"apiVersion": "2018-06-01",
			"properties": {
				"annotations": [],
				"type": "AzureBlobStorage",
				"typeProperties": {
					"connectionString": "[parameters('LinkedService3790_connectionString')]"
				},
				"connectVia": {
					"referenceName": "TestManyLS",
					"type": "IntegrationRuntimeReference"
				}
			},
			"dependsOn": []
		},
		{
			"name": "[concat(parameters('factoryName'), '/LinkedService3791')]",
			"type": "Microsoft.DataFactory/factories/linkedServices",
			"apiVersion": "2018-06-01",
			"properties": {
				"annotations": [],
				"type": "AzureBlobStorage",
				"typeProperties": {
					"connectionString": "[parameters('LinkedService3791_connectionString')]"
				},
				"connectVia": {
					"referenceName": "TestManyLS",
					"type": "IntegrationRuntimeReference"
				}
			},
			"dependsOn": []
		},
		{
			"name": "[concat(parameters('factoryName'), '/LinkedService3792')]",
			"type": "Microsoft.DataFactory/factories/linkedServices",
			"apiVersion": "2018-06-01",
			"properties": {
				"annotations": [],
				"type": "AzureBlobStorage",
				"typeProperties": {
					"connectionString": "[parameters('LinkedService3792_connectionString')]"
				},
				"connectVia": {
					"referenceName": "TestManyLS",
					"type": "IntegrationRuntimeReference"
				}
			},
			"dependsOn": []
		},
		{
			"name": "[concat(parameters('factoryName'), '/LinkedService3793')]",
			"type": "Microsoft.DataFactory/factories/linkedServices",
			"apiVersion": "2018-06-01",
			"properties": {
				"annotations": [],
				"type": "AzureBlobStorage",
				"typeProperties": {
					"connectionString": "[parameters('LinkedService3793_connectionString')]"
				},
				"connectVia": {
					"referenceName": "TestManyLS",
					"type": "IntegrationRuntimeReference"
				}
			},
			"dependsOn": []
		},
		{
			"name": "[concat(parameters('factoryName'), '/LinkedService3794')]",
			"type": "Microsoft.DataFactory/factories/linkedServices",
			"apiVersion": "2018-06-01",
			"properties": {
				"annotations": [],
				"type": "AzureBlobStorage",
				"typeProperties": {
					"connectionString": "[parameters('LinkedService3794_connectionString')]"
				},
				"connectVia": {
					"referenceName": "TestManyLS",
					"type": "IntegrationRuntimeReference"
				}
			},
			"dependsOn": []
		},
		{
			"name": "[concat(parameters('factoryName'), '/LinkedService3795')]",
			"type": "Microsoft.DataFactory/factories/linkedServices",
			"apiVersion": "2018-06-01",
			"properties": {
				"annotations": [],
				"type": "AzureBlobStorage",
				"typeProperties": {
					"connectionString": "[parameters('LinkedService3795_connectionString')]"
				},
				"connectVia": {
					"referenceName": "TestManyLS",
					"type": "IntegrationRuntimeReference"
				}
			},
			"dependsOn": []
		},
		{
			"name": "[concat(parameters('factoryName'), '/LinkedService3796')]",
			"type": "Microsoft.DataFactory/factories/linkedServices",
			"apiVersion": "2018-06-01",
			"properties": {
				"annotations": [],
				"type": "AzureBlobStorage",
				"typeProperties": {
					"connectionString": "[parameters('LinkedService3796_connectionString')]"
				},
				"connectVia": {
					"referenceName": "TestManyLS",
					"type": "IntegrationRuntimeReference"
				}
			},
			"dependsOn": []
		},
		{
			"name": "[concat(parameters('factoryName'), '/LinkedService3797')]",
			"type": "Microsoft.DataFactory/factories/linkedServices",
			"apiVersion": "2018-06-01",
			"properties": {
				"annotations": [],
				"type": "AzureBlobStorage",
				"typeProperties": {
					"connectionString": "[parameters('LinkedService3797_connectionString')]"
				},
				"connectVia": {
					"referenceName": "TestManyLS",
					"type": "IntegrationRuntimeReference"
				}
			},
			"dependsOn": []
		},
		{
			"name": "[concat(parameters('factoryName'), '/LinkedService3798')]",
			"type": "Microsoft.DataFactory/factories/linkedServices",
			"apiVersion": "2018-06-01",
			"properties": {
				"annotations": [],
				"type": "AzureBlobStorage",
				"typeProperties": {
					"connectionString": "[parameters('LinkedService3798_connectionString')]"
				},
				"connectVia": {
					"referenceName": "TestManyLS",
					"type": "IntegrationRuntimeReference"
				}
			},
			"dependsOn": []
		},
		{
			"name": "[concat(parameters('factoryName'), '/LinkedService3799')]",
			"type": "Microsoft.DataFactory/factories/linkedServices",
			"apiVersion": "2018-06-01",
			"properties": {
				"annotations": [],
				"type": "AzureBlobStorage",
				"typeProperties": {
					"connectionString": "[parameters('LinkedService3799_connectionString')]"
				},
				"connectVia": {
					"referenceName": "TestManyLS",
					"type": "IntegrationRuntimeReference"
				}
			},
			"dependsOn": []
		},
		{
			"name": "[concat(parameters('factoryName'), '/LinkedService38')]",
			"type": "Microsoft.DataFactory/factories/linkedServices",
			"apiVersion": "2018-06-01",
			"properties": {
				"annotations": [],
				"type": "AzureBlobStorage",
				"typeProperties": {
					"connectionString": "[parameters('LinkedService38_connectionString')]"
				},
				"connectVia": {
					"referenceName": "TestManyLS",
					"type": "IntegrationRuntimeReference"
				}
			},
			"dependsOn": []
		},
		{
			"name": "[concat(parameters('factoryName'), '/LinkedService380')]",
			"type": "Microsoft.DataFactory/factories/linkedServices",
			"apiVersion": "2018-06-01",
			"properties": {
				"annotations": [],
				"type": "AzureBlobStorage",
				"typeProperties": {
					"connectionString": "[parameters('LinkedService380_connectionString')]"
				},
				"connectVia": {
					"referenceName": "TestManyLS",
					"type": "IntegrationRuntimeReference"
				}
			},
			"dependsOn": []
		},
		{
			"name": "[concat(parameters('factoryName'), '/LinkedService3800')]",
			"type": "Microsoft.DataFactory/factories/linkedServices",
			"apiVersion": "2018-06-01",
			"properties": {
				"annotations": [],
				"type": "AzureBlobStorage",
				"typeProperties": {
					"connectionString": "[parameters('LinkedService3800_connectionString')]"
				},
				"connectVia": {
					"referenceName": "TestManyLS",
					"type": "IntegrationRuntimeReference"
				}
			},
			"dependsOn": []
		},
		{
			"name": "[concat(parameters('factoryName'), '/LinkedService3801')]",
			"type": "Microsoft.DataFactory/factories/linkedServices",
			"apiVersion": "2018-06-01",
			"properties": {
				"annotations": [],
				"type": "AzureBlobStorage",
				"typeProperties": {
					"connectionString": "[parameters('LinkedService3801_connectionString')]"
				},
				"connectVia": {
					"referenceName": "TestManyLS",
					"type": "IntegrationRuntimeReference"
				}
			},
			"dependsOn": []
		}
	]
}