{
	"$schema": "http://schema.management.azure.com/schemas/2015-01-01/deploymentTemplate.json#",
	"contentVersion": "1.0.0.0",
	"parameters": {
		"factoryName": {
			"type": "string",
			"metadata": "Data Factory name",
			"defaultValue": "KUSONG-PROD-IR"
		},
		"LinkedService1192_connectionString": {
			"type": "secureString",
			"metadata": "Secure string for 'connectionString' of 'LinkedService1192'"
		},
		"LinkedService1193_connectionString": {
			"type": "secureString",
			"metadata": "Secure string for 'connectionString' of 'LinkedService1193'"
		},
		"LinkedService1194_connectionString": {
			"type": "secureString",
			"metadata": "Secure string for 'connectionString' of 'LinkedService1194'"
		},
		"LinkedService1195_connectionString": {
			"type": "secureString",
			"metadata": "Secure string for 'connectionString' of 'LinkedService1195'"
		},
		"LinkedService1196_connectionString": {
			"type": "secureString",
			"metadata": "Secure string for 'connectionString' of 'LinkedService1196'"
		},
		"LinkedService1197_connectionString": {
			"type": "secureString",
			"metadata": "Secure string for 'connectionString' of 'LinkedService1197'"
		},
		"LinkedService1198_connectionString": {
			"type": "secureString",
			"metadata": "Secure string for 'connectionString' of 'LinkedService1198'"
		},
		"LinkedService1199_connectionString": {
			"type": "secureString",
			"metadata": "Secure string for 'connectionString' of 'LinkedService1199'"
		},
		"LinkedService12_connectionString": {
			"type": "secureString",
			"metadata": "Secure string for 'connectionString' of 'LinkedService12'"
		},
		"LinkedService120_connectionString": {
			"type": "secureString",
			"metadata": "Secure string for 'connectionString' of 'LinkedService120'"
		},
		"LinkedService1200_connectionString": {
			"type": "secureString",
			"metadata": "Secure string for 'connectionString' of 'LinkedService1200'"
		},
		"LinkedService1201_connectionString": {
			"type": "secureString",
			"metadata": "Secure string for 'connectionString' of 'LinkedService1201'"
		},
		"LinkedService1202_connectionString": {
			"type": "secureString",
			"metadata": "Secure string for 'connectionString' of 'LinkedService1202'"
		},
		"LinkedService1203_connectionString": {
			"type": "secureString",
			"metadata": "Secure string for 'connectionString' of 'LinkedService1203'"
		},
		"LinkedService1204_connectionString": {
			"type": "secureString",
			"metadata": "Secure string for 'connectionString' of 'LinkedService1204'"
		},
		"LinkedService1205_connectionString": {
			"type": "secureString",
			"metadata": "Secure string for 'connectionString' of 'LinkedService1205'"
		},
		"LinkedService1206_connectionString": {
			"type": "secureString",
			"metadata": "Secure string for 'connectionString' of 'LinkedService1206'"
		},
		"LinkedService1207_connectionString": {
			"type": "secureString",
			"metadata": "Secure string for 'connectionString' of 'LinkedService1207'"
		},
		"LinkedService1208_connectionString": {
			"type": "secureString",
			"metadata": "Secure string for 'connectionString' of 'LinkedService1208'"
		},
		"LinkedService1209_connectionString": {
			"type": "secureString",
			"metadata": "Secure string for 'connectionString' of 'LinkedService1209'"
		}
	},
	"variables": {
		"factoryId": "[concat('Microsoft.DataFactory/factories/', parameters('factoryName'))]"
	},
	"resources": [
		{
			"name": "[concat(parameters('factoryName'), '/LinkedService1192')]",
			"type": "Microsoft.DataFactory/factories/linkedServices",
			"apiVersion": "2018-06-01",
			"properties": {
				"annotations": [],
				"type": "AzureBlobStorage",
				"typeProperties": {
					"connectionString": "[parameters('LinkedService1192_connectionString')]"
				},
				"connectVia": {
					"referenceName": "TestManyLS",
					"type": "IntegrationRuntimeReference"
				}
			},
			"dependsOn": []
		},
		{
			"name": "[concat(parameters('factoryName'), '/LinkedService1193')]",
			"type": "Microsoft.DataFactory/factories/linkedServices",
			"apiVersion": "2018-06-01",
			"properties": {
				"annotations": [],
				"type": "AzureBlobStorage",
				"typeProperties": {
					"connectionString": "[parameters('LinkedService1193_connectionString')]"
				},
				"connectVia": {
					"referenceName": "TestManyLS",
					"type": "IntegrationRuntimeReference"
				}
			},
			"dependsOn": []
		},
		{
			"name": "[concat(parameters('factoryName'), '/LinkedService1194')]",
			"type": "Microsoft.DataFactory/factories/linkedServices",
			"apiVersion": "2018-06-01",
			"properties": {
				"annotations": [],
				"type": "AzureBlobStorage",
				"typeProperties": {
					"connectionString": "[parameters('LinkedService1194_connectionString')]"
				},
				"connectVia": {
					"referenceName": "TestManyLS",
					"type": "IntegrationRuntimeReference"
				}
			},
			"dependsOn": []
		},
		{
			"name": "[concat(parameters('factoryName'), '/LinkedService1195')]",
			"type": "Microsoft.DataFactory/factories/linkedServices",
			"apiVersion": "2018-06-01",
			"properties": {
				"annotations": [],
				"type": "AzureBlobStorage",
				"typeProperties": {
					"connectionString": "[parameters('LinkedService1195_connectionString')]"
				},
				"connectVia": {
					"referenceName": "TestManyLS",
					"type": "IntegrationRuntimeReference"
				}
			},
			"dependsOn": []
		},
		{
			"name": "[concat(parameters('factoryName'), '/LinkedService1196')]",
			"type": "Microsoft.DataFactory/factories/linkedServices",
			"apiVersion": "2018-06-01",
			"properties": {
				"annotations": [],
				"type": "AzureBlobStorage",
				"typeProperties": {
					"connectionString": "[parameters('LinkedService1196_connectionString')]"
				},
				"connectVia": {
					"referenceName": "TestManyLS",
					"type": "IntegrationRuntimeReference"
				}
			},
			"dependsOn": []
		},
		{
			"name": "[concat(parameters('factoryName'), '/LinkedService1197')]",
			"type": "Microsoft.DataFactory/factories/linkedServices",
			"apiVersion": "2018-06-01",
			"properties": {
				"annotations": [],
				"type": "AzureBlobStorage",
				"typeProperties": {
					"connectionString": "[parameters('LinkedService1197_connectionString')]"
				},
				"connectVia": {
					"referenceName": "TestManyLS",
					"type": "IntegrationRuntimeReference"
				}
			},
			"dependsOn": []
		},
		{
			"name": "[concat(parameters('factoryName'), '/LinkedService1198')]",
			"type": "Microsoft.DataFactory/factories/linkedServices",
			"apiVersion": "2018-06-01",
			"properties": {
				"annotations": [],
				"type": "AzureBlobStorage",
				"typeProperties": {
					"connectionString": "[parameters('LinkedService1198_connectionString')]"
				},
				"connectVia": {
					"referenceName": "TestManyLS",
					"type": "IntegrationRuntimeReference"
				}
			},
			"dependsOn": []
		},
		{
			"name": "[concat(parameters('factoryName'), '/LinkedService1199')]",
			"type": "Microsoft.DataFactory/factories/linkedServices",
			"apiVersion": "2018-06-01",
			"properties": {
				"annotations": [],
				"type": "AzureBlobStorage",
				"typeProperties": {
					"connectionString": "[parameters('LinkedService1199_connectionString')]"
				},
				"connectVia": {
					"referenceName": "TestManyLS",
					"type": "IntegrationRuntimeReference"
				}
			},
			"dependsOn": []
		},
		{
			"name": "[concat(parameters('factoryName'), '/LinkedService12')]",
			"type": "Microsoft.DataFactory/factories/linkedServices",
			"apiVersion": "2018-06-01",
			"properties": {
				"annotations": [],
				"type": "AzureBlobStorage",
				"typeProperties": {
					"connectionString": "[parameters('LinkedService12_connectionString')]"
				},
				"connectVia": {
					"referenceName": "TestManyLS",
					"type": "IntegrationRuntimeReference"
				}
			},
			"dependsOn": []
		},
		{
			"name": "[concat(parameters('factoryName'), '/LinkedService120')]",
			"type": "Microsoft.DataFactory/factories/linkedServices",
			"apiVersion": "2018-06-01",
			"properties": {
				"annotations": [],
				"type": "AzureBlobStorage",
				"typeProperties": {
					"connectionString": "[parameters('LinkedService120_connectionString')]"
				},
				"connectVia": {
					"referenceName": "TestManyLS",
					"type": "IntegrationRuntimeReference"
				}
			},
			"dependsOn": []
		},
		{
			"name": "[concat(parameters('factoryName'), '/LinkedService1200')]",
			"type": "Microsoft.DataFactory/factories/linkedServices",
			"apiVersion": "2018-06-01",
			"properties": {
				"annotations": [],
				"type": "AzureBlobStorage",
				"typeProperties": {
					"connectionString": "[parameters('LinkedService1200_connectionString')]"
				},
				"connectVia": {
					"referenceName": "TestManyLS",
					"type": "IntegrationRuntimeReference"
				}
			},
			"dependsOn": []
		},
		{
			"name": "[concat(parameters('factoryName'), '/LinkedService1201')]",
			"type": "Microsoft.DataFactory/factories/linkedServices",
			"apiVersion": "2018-06-01",
			"properties": {
				"annotations": [],
				"type": "AzureBlobStorage",
				"typeProperties": {
					"connectionString": "[parameters('LinkedService1201_connectionString')]"
				},
				"connectVia": {
					"referenceName": "TestManyLS",
					"type": "IntegrationRuntimeReference"
				}
			},
			"dependsOn": []
		},
		{
			"name": "[concat(parameters('factoryName'), '/LinkedService1202')]",
			"type": "Microsoft.DataFactory/factories/linkedServices",
			"apiVersion": "2018-06-01",
			"properties": {
				"annotations": [],
				"type": "AzureBlobStorage",
				"typeProperties": {
					"connectionString": "[parameters('LinkedService1202_connectionString')]"
				},
				"connectVia": {
					"referenceName": "TestManyLS",
					"type": "IntegrationRuntimeReference"
				}
			},
			"dependsOn": []
		},
		{
			"name": "[concat(parameters('factoryName'), '/LinkedService1203')]",
			"type": "Microsoft.DataFactory/factories/linkedServices",
			"apiVersion": "2018-06-01",
			"properties": {
				"annotations": [],
				"type": "AzureBlobStorage",
				"typeProperties": {
					"connectionString": "[parameters('LinkedService1203_connectionString')]"
				},
				"connectVia": {
					"referenceName": "TestManyLS",
					"type": "IntegrationRuntimeReference"
				}
			},
			"dependsOn": []
		},
		{
			"name": "[concat(parameters('factoryName'), '/LinkedService1204')]",
			"type": "Microsoft.DataFactory/factories/linkedServices",
			"apiVersion": "2018-06-01",
			"properties": {
				"annotations": [],
				"type": "AzureBlobStorage",
				"typeProperties": {
					"connectionString": "[parameters('LinkedService1204_connectionString')]"
				},
				"connectVia": {
					"referenceName": "TestManyLS",
					"type": "IntegrationRuntimeReference"
				}
			},
			"dependsOn": []
		},
		{
			"name": "[concat(parameters('factoryName'), '/LinkedService1205')]",
			"type": "Microsoft.DataFactory/factories/linkedServices",
			"apiVersion": "2018-06-01",
			"properties": {
				"annotations": [],
				"type": "AzureBlobStorage",
				"typeProperties": {
					"connectionString": "[parameters('LinkedService1205_connectionString')]"
				},
				"connectVia": {
					"referenceName": "TestManyLS",
					"type": "IntegrationRuntimeReference"
				}
			},
			"dependsOn": []
		},
		{
			"name": "[concat(parameters('factoryName'), '/LinkedService1206')]",
			"type": "Microsoft.DataFactory/factories/linkedServices",
			"apiVersion": "2018-06-01",
			"properties": {
				"annotations": [],
				"type": "AzureBlobStorage",
				"typeProperties": {
					"connectionString": "[parameters('LinkedService1206_connectionString')]"
				},
				"connectVia": {
					"referenceName": "TestManyLS",
					"type": "IntegrationRuntimeReference"
				}
			},
			"dependsOn": []
		},
		{
			"name": "[concat(parameters('factoryName'), '/LinkedService1207')]",
			"type": "Microsoft.DataFactory/factories/linkedServices",
			"apiVersion": "2018-06-01",
			"properties": {
				"annotations": [],
				"type": "AzureBlobStorage",
				"typeProperties": {
					"connectionString": "[parameters('LinkedService1207_connectionString')]"
				},
				"connectVia": {
					"referenceName": "TestManyLS",
					"type": "IntegrationRuntimeReference"
				}
			},
			"dependsOn": []
		},
		{
			"name": "[concat(parameters('factoryName'), '/LinkedService1208')]",
			"type": "Microsoft.DataFactory/factories/linkedServices",
			"apiVersion": "2018-06-01",
			"properties": {
				"annotations": [],
				"type": "AzureBlobStorage",
				"typeProperties": {
					"connectionString": "[parameters('LinkedService1208_connectionString')]"
				},
				"connectVia": {
					"referenceName": "TestManyLS",
					"type": "IntegrationRuntimeReference"
				}
			},
			"dependsOn": []
		},
		{
			"name": "[concat(parameters('factoryName'), '/LinkedService1209')]",
			"type": "Microsoft.DataFactory/factories/linkedServices",
			"apiVersion": "2018-06-01",
			"properties": {
				"annotations": [],
				"type": "AzureBlobStorage",
				"typeProperties": {
					"connectionString": "[parameters('LinkedService1209_connectionString')]"
				},
				"connectVia": {
					"referenceName": "TestManyLS",
					"type": "IntegrationRuntimeReference"
				}
			},
			"dependsOn": []
		}
	]
}