{
	"$schema": "http://schema.management.azure.com/schemas/2015-01-01/deploymentTemplate.json#",
	"contentVersion": "1.0.0.0",
	"parameters": {
		"factoryName": {
			"type": "string",
			"metadata": "Data Factory name",
			"defaultValue": "KUSONG-PROD-IR"
		},
		"LinkedService3587_connectionString": {
			"type": "secureString",
			"metadata": "Secure string for 'connectionString' of 'LinkedService3587'"
		},
		"LinkedService3588_connectionString": {
			"type": "secureString",
			"metadata": "Secure string for 'connectionString' of 'LinkedService3588'"
		},
		"LinkedService3589_connectionString": {
			"type": "secureString",
			"metadata": "Secure string for 'connectionString' of 'LinkedService3589'"
		},
		"LinkedService359_connectionString": {
			"type": "secureString",
			"metadata": "Secure string for 'connectionString' of 'LinkedService359'"
		},
		"LinkedService3590_connectionString": {
			"type": "secureString",
			"metadata": "Secure string for 'connectionString' of 'LinkedService3590'"
		},
		"LinkedService3591_connectionString": {
			"type": "secureString",
			"metadata": "Secure string for 'connectionString' of 'LinkedService3591'"
		},
		"LinkedService3592_connectionString": {
			"type": "secureString",
			"metadata": "Secure string for 'connectionString' of 'LinkedService3592'"
		},
		"LinkedService3593_connectionString": {
			"type": "secureString",
			"metadata": "Secure string for 'connectionString' of 'LinkedService3593'"
		},
		"LinkedService3594_connectionString": {
			"type": "secureString",
			"metadata": "Secure string for 'connectionString' of 'LinkedService3594'"
		},
		"LinkedService3595_connectionString": {
			"type": "secureString",
			"metadata": "Secure string for 'connectionString' of 'LinkedService3595'"
		},
		"LinkedService3596_connectionString": {
			"type": "secureString",
			"metadata": "Secure string for 'connectionString' of 'LinkedService3596'"
		},
		"LinkedService3597_connectionString": {
			"type": "secureString",
			"metadata": "Secure string for 'connectionString' of 'LinkedService3597'"
		},
		"LinkedService3598_connectionString": {
			"type": "secureString",
			"metadata": "Secure string for 'connectionString' of 'LinkedService3598'"
		},
		"LinkedService3599_connectionString": {
			"type": "secureString",
			"metadata": "Secure string for 'connectionString' of 'LinkedService3599'"
		},
		"LinkedService36_connectionString": {
			"type": "secureString",
			"metadata": "Secure string for 'connectionString' of 'LinkedService36'"
		},
		"LinkedService360_connectionString": {
			"type": "secureString",
			"metadata": "Secure string for 'connectionString' of 'LinkedService360'"
		},
		"LinkedService3600_connectionString": {
			"type": "secureString",
			"metadata": "Secure string for 'connectionString' of 'LinkedService3600'"
		},
		"LinkedService3601_connectionString": {
			"type": "secureString",
			"metadata": "Secure string for 'connectionString' of 'LinkedService3601'"
		},
		"LinkedService3602_connectionString": {
			"type": "secureString",
			"metadata": "Secure string for 'connectionString' of 'LinkedService3602'"
		},
		"LinkedService3603_connectionString": {
			"type": "secureString",
			"metadata": "Secure string for 'connectionString' of 'LinkedService3603'"
		}
	},
	"variables": {
		"factoryId": "[concat('Microsoft.DataFactory/factories/', parameters('factoryName'))]"
	},
	"resources": [
		{
			"name": "[concat(parameters('factoryName'), '/LinkedService3587')]",
			"type": "Microsoft.DataFactory/factories/linkedServices",
			"apiVersion": "2018-06-01",
			"properties": {
				"annotations": [],
				"type": "AzureBlobStorage",
				"typeProperties": {
					"connectionString": "[parameters('LinkedService3587_connectionString')]"
				},
				"connectVia": {
					"referenceName": "TestManyLS",
					"type": "IntegrationRuntimeReference"
				}
			},
			"dependsOn": []
		},
		{
			"name": "[concat(parameters('factoryName'), '/LinkedService3588')]",
			"type": "Microsoft.DataFactory/factories/linkedServices",
			"apiVersion": "2018-06-01",
			"properties": {
				"annotations": [],
				"type": "AzureBlobStorage",
				"typeProperties": {
					"connectionString": "[parameters('LinkedService3588_connectionString')]"
				},
				"connectVia": {
					"referenceName": "TestManyLS",
					"type": "IntegrationRuntimeReference"
				}
			},
			"dependsOn": []
		},
		{
			"name": "[concat(parameters('factoryName'), '/LinkedService3589')]",
			"type": "Microsoft.DataFactory/factories/linkedServices",
			"apiVersion": "2018-06-01",
			"properties": {
				"annotations": [],
				"type": "AzureBlobStorage",
				"typeProperties": {
					"connectionString": "[parameters('LinkedService3589_connectionString')]"
				},
				"connectVia": {
					"referenceName": "TestManyLS",
					"type": "IntegrationRuntimeReference"
				}
			},
			"dependsOn": []
		},
		{
			"name": "[concat(parameters('factoryName'), '/LinkedService359')]",
			"type": "Microsoft.DataFactory/factories/linkedServices",
			"apiVersion": "2018-06-01",
			"properties": {
				"annotations": [],
				"type": "AzureBlobStorage",
				"typeProperties": {
					"connectionString": "[parameters('LinkedService359_connectionString')]"
				},
				"connectVia": {
					"referenceName": "TestManyLS",
					"type": "IntegrationRuntimeReference"
				}
			},
			"dependsOn": []
		},
		{
			"name": "[concat(parameters('factoryName'), '/LinkedService3590')]",
			"type": "Microsoft.DataFactory/factories/linkedServices",
			"apiVersion": "2018-06-01",
			"properties": {
				"annotations": [],
				"type": "AzureBlobStorage",
				"typeProperties": {
					"connectionString": "[parameters('LinkedService3590_connectionString')]"
				},
				"connectVia": {
					"referenceName": "TestManyLS",
					"type": "IntegrationRuntimeReference"
				}
			},
			"dependsOn": []
		},
		{
			"name": "[concat(parameters('factoryName'), '/LinkedService3591')]",
			"type": "Microsoft.DataFactory/factories/linkedServices",
			"apiVersion": "2018-06-01",
			"properties": {
				"annotations": [],
				"type": "AzureBlobStorage",
				"typeProperties": {
					"connectionString": "[parameters('LinkedService3591_connectionString')]"
				},
				"connectVia": {
					"referenceName": "TestManyLS",
					"type": "IntegrationRuntimeReference"
				}
			},
			"dependsOn": []
		},
		{
			"name": "[concat(parameters('factoryName'), '/LinkedService3592')]",
			"type": "Microsoft.DataFactory/factories/linkedServices",
			"apiVersion": "2018-06-01",
			"properties": {
				"annotations": [],
				"type": "AzureBlobStorage",
				"typeProperties": {
					"connectionString": "[parameters('LinkedService3592_connectionString')]"
				},
				"connectVia": {
					"referenceName": "TestManyLS",
					"type": "IntegrationRuntimeReference"
				}
			},
			"dependsOn": []
		},
		{
			"name": "[concat(parameters('factoryName'), '/LinkedService3593')]",
			"type": "Microsoft.DataFactory/factories/linkedServices",
			"apiVersion": "2018-06-01",
			"properties": {
				"annotations": [],
				"type": "AzureBlobStorage",
				"typeProperties": {
					"connectionString": "[parameters('LinkedService3593_connectionString')]"
				},
				"connectVia": {
					"referenceName": "TestManyLS",
					"type": "IntegrationRuntimeReference"
				}
			},
			"dependsOn": []
		},
		{
			"name": "[concat(parameters('factoryName'), '/LinkedService3594')]",
			"type": "Microsoft.DataFactory/factories/linkedServices",
			"apiVersion": "2018-06-01",
			"properties": {
				"annotations": [],
				"type": "AzureBlobStorage",
				"typeProperties": {
					"connectionString": "[parameters('LinkedService3594_connectionString')]"
				},
				"connectVia": {
					"referenceName": "TestManyLS",
					"type": "IntegrationRuntimeReference"
				}
			},
			"dependsOn": []
		},
		{
			"name": "[concat(parameters('factoryName'), '/LinkedService3595')]",
			"type": "Microsoft.DataFactory/factories/linkedServices",
			"apiVersion": "2018-06-01",
			"properties": {
				"annotations": [],
				"type": "AzureBlobStorage",
				"typeProperties": {
					"connectionString": "[parameters('LinkedService3595_connectionString')]"
				},
				"connectVia": {
					"referenceName": "TestManyLS",
					"type": "IntegrationRuntimeReference"
				}
			},
			"dependsOn": []
		},
		{
			"name": "[concat(parameters('factoryName'), '/LinkedService3596')]",
			"type": "Microsoft.DataFactory/factories/linkedServices",
			"apiVersion": "2018-06-01",
			"properties": {
				"annotations": [],
				"type": "AzureBlobStorage",
				"typeProperties": {
					"connectionString": "[parameters('LinkedService3596_connectionString')]"
				},
				"connectVia": {
					"referenceName": "TestManyLS",
					"type": "IntegrationRuntimeReference"
				}
			},
			"dependsOn": []
		},
		{
			"name": "[concat(parameters('factoryName'), '/LinkedService3597')]",
			"type": "Microsoft.DataFactory/factories/linkedServices",
			"apiVersion": "2018-06-01",
			"properties": {
				"annotations": [],
				"type": "AzureBlobStorage",
				"typeProperties": {
					"connectionString": "[parameters('LinkedService3597_connectionString')]"
				},
				"connectVia": {
					"referenceName": "TestManyLS",
					"type": "IntegrationRuntimeReference"
				}
			},
			"dependsOn": []
		},
		{
			"name": "[concat(parameters('factoryName'), '/LinkedService3598')]",
			"type": "Microsoft.DataFactory/factories/linkedServices",
			"apiVersion": "2018-06-01",
			"properties": {
				"annotations": [],
				"type": "AzureBlobStorage",
				"typeProperties": {
					"connectionString": "[parameters('LinkedService3598_connectionString')]"
				},
				"connectVia": {
					"referenceName": "TestManyLS",
					"type": "IntegrationRuntimeReference"
				}
			},
			"dependsOn": []
		},
		{
			"name": "[concat(parameters('factoryName'), '/LinkedService3599')]",
			"type": "Microsoft.DataFactory/factories/linkedServices",
			"apiVersion": "2018-06-01",
			"properties": {
				"annotations": [],
				"type": "AzureBlobStorage",
				"typeProperties": {
					"connectionString": "[parameters('LinkedService3599_connectionString')]"
				},
				"connectVia": {
					"referenceName": "TestManyLS",
					"type": "IntegrationRuntimeReference"
				}
			},
			"dependsOn": []
		},
		{
			"name": "[concat(parameters('factoryName'), '/LinkedService36')]",
			"type": "Microsoft.DataFactory/factories/linkedServices",
			"apiVersion": "2018-06-01",
			"properties": {
				"annotations": [],
				"type": "AzureBlobStorage",
				"typeProperties": {
					"connectionString": "[parameters('LinkedService36_connectionString')]"
				},
				"connectVia": {
					"referenceName": "TestManyLS",
					"type": "IntegrationRuntimeReference"
				}
			},
			"dependsOn": []
		},
		{
			"name": "[concat(parameters('factoryName'), '/LinkedService360')]",
			"type": "Microsoft.DataFactory/factories/linkedServices",
			"apiVersion": "2018-06-01",
			"properties": {
				"annotations": [],
				"type": "AzureBlobStorage",
				"typeProperties": {
					"connectionString": "[parameters('LinkedService360_connectionString')]"
				},
				"connectVia": {
					"referenceName": "TestManyLS",
					"type": "IntegrationRuntimeReference"
				}
			},
			"dependsOn": []
		},
		{
			"name": "[concat(parameters('factoryName'), '/LinkedService3600')]",
			"type": "Microsoft.DataFactory/factories/linkedServices",
			"apiVersion": "2018-06-01",
			"properties": {
				"annotations": [],
				"type": "AzureBlobStorage",
				"typeProperties": {
					"connectionString": "[parameters('LinkedService3600_connectionString')]"
				},
				"connectVia": {
					"referenceName": "TestManyLS",
					"type": "IntegrationRuntimeReference"
				}
			},
			"dependsOn": []
		},
		{
			"name": "[concat(parameters('factoryName'), '/LinkedService3601')]",
			"type": "Microsoft.DataFactory/factories/linkedServices",
			"apiVersion": "2018-06-01",
			"properties": {
				"annotations": [],
				"type": "AzureBlobStorage",
				"typeProperties": {
					"connectionString": "[parameters('LinkedService3601_connectionString')]"
				},
				"connectVia": {
					"referenceName": "TestManyLS",
					"type": "IntegrationRuntimeReference"
				}
			},
			"dependsOn": []
		},
		{
			"name": "[concat(parameters('factoryName'), '/LinkedService3602')]",
			"type": "Microsoft.DataFactory/factories/linkedServices",
			"apiVersion": "2018-06-01",
			"properties": {
				"annotations": [],
				"type": "AzureBlobStorage",
				"typeProperties": {
					"connectionString": "[parameters('LinkedService3602_connectionString')]"
				},
				"connectVia": {
					"referenceName": "TestManyLS",
					"type": "IntegrationRuntimeReference"
				}
			},
			"dependsOn": []
		},
		{
			"name": "[concat(parameters('factoryName'), '/LinkedService3603')]",
			"type": "Microsoft.DataFactory/factories/linkedServices",
			"apiVersion": "2018-06-01",
			"properties": {
				"annotations": [],
				"type": "AzureBlobStorage",
				"typeProperties": {
					"connectionString": "[parameters('LinkedService3603_connectionString')]"
				},
				"connectVia": {
					"referenceName": "TestManyLS",
					"type": "IntegrationRuntimeReference"
				}
			},
			"dependsOn": []
		}
	]
}